tests/__init__.py
tests/test_transliterator.py
tibetan_sanskrit_transliteration/__init__.py
tibetan_sanskrit_transliteration/normalizer.py
tibetan_sanskrit_transliteration/transliterator.py
tibetan_sanskrit_transliteration-0.1.3.dist-info/METADATA
tibetan_sanskrit_transliteration-0.1.3.dist-info/WHEEL
tibetan_sanskrit_transliteration-0.1.3.dist-info/top_level.txt
tibetan_sanskrit_transliteration-0.1.3.dist-info/RECORD
