Metadata-Version: 2.4
Name: tibetan-sanskrit-transliteration
Version: 0.1.3
Summary: Transliterate Tibetan-encoded Sanskrit mantras to IAST and phonetics
Author: Padmakara
License: MIT
Project-URL: Homepage, https://github.com/jerefrer/tibetan-sanskrit-transliteration-py
Project-URL: Repository, https://github.com/jerefrer/tibetan-sanskrit-transliteration-py
Keywords: tibetan,sanskrit,transliteration,iast,phonetics,mantra
Classifier: Development Status :: 4 - Beta
Classifier: Intended Audience :: Developers
Classifier: License :: OSI Approved :: MIT License
Classifier: Programming Language :: Python :: 3
Classifier: Programming Language :: Python :: 3.8
Classifier: Programming Language :: Python :: 3.9
Classifier: Programming Language :: Python :: 3.10
Classifier: Programming Language :: Python :: 3.11
Classifier: Programming Language :: Python :: 3.12
Requires-Python: >=3.8
Requires-Dist: tibetan-sanskrit-transliteration-data>=0.1.3
